rex/__init__.py
rex/version.py
rex/cmds/__init__.py
rex/cmds/emb.py
rex/cmds/gen_conf.py
rex/cmds/new.py
rex/cmds/train.py
rex/data/__init__.py
rex/data/collate_fn.py
rex/data/data_manager.py
rex/data/dataset.py
rex/data/instance.py
rex/data/label_encoder.py
rex/data/vocab.py
rex/data/transforms/__init__.py
rex/data/transforms/bag_re.py
rex/data/transforms/base.py
rex/data/transforms/entity_re.py
rex/data/transforms/mrc_ner.py
rex/data/transforms/sent_re.py
rex/metrics/__init__.py
rex/metrics/base.py
rex/metrics/classification.py
rex/metrics/mrc_ner.py
rex/metrics/tagging.py
rex/metrics/triple.py
rex/models/__init__.py
rex/models/bag_pcnn.py
rex/models/base.py
rex/models/casrel.py
rex/models/mrc_ner.py
rex/models/sent_pcnn.py
rex/modules/__init__.py
rex/modules/cnn.py
rex/modules/crf.py
rex/modules/dropout.py
rex/modules/ffn.py
rex/modules/pcnn.py
rex/modules/span.py
rex/modules/embeddings/__init__.py
rex/modules/embeddings/static_embedding.py
rex/optim/__init__.py
rex/optim/lion.py
rex/tasks/__init__.py
rex/tasks/base_task.py
rex/tasks/entity_relation_extraction.py
rex/tasks/named_entity_recognition.py
rex/tasks/relation_extraction.py
rex/tasks/simple_metric_task.py
rex/tasks/simple_task.py
rex/templates/.gitignore
rex/templates/README.md
rex/templates/custom.yaml
rex/templates/run.sh
rex/templates/data/download.py
rex/templates/src/__init__.py
rex/templates/src/metric.py
rex/templates/src/model.py
rex/templates/src/task.py
rex/templates/src/transform.py
rex/utils/__init__.py
rex/utils/batch.py
rex/utils/build_emb.py
rex/utils/config.py
rex/utils/deprecation.py
rex/utils/dict.py
rex/utils/initialization.py
rex/utils/io.py
rex/utils/iteration.py
rex/utils/logging.py
rex/utils/mask.py
rex/utils/param.py
rex/utils/position.py
rex/utils/progress_bar.py
rex/utils/random.py
rex/utils/registry.py
rex/utils/scinum.py
rex/utils/segmentation.py
rex/utils/span.py
rex/utils/tagging.py
rex/utils/tensor_move.py
rex/utils/vars.py
rex/utils/wrapper.py
pytorch_rex-0.1.9.dist-info/LICENSE
pytorch_rex-0.1.9.dist-info/METADATA
pytorch_rex-0.1.9.dist-info/WHEEL
pytorch_rex-0.1.9.dist-info/entry_points.txt
pytorch_rex-0.1.9.dist-info/top_level.txt
pytorch_rex-0.1.9.dist-info/RECORD
