Metadata-Version: 2.1
Name: pytorch-rex
Version: 0.1.9
Summary: A toolkit for Relation Extraction and more...
Home-page: https://github.com/Spico197/REx
Author: Tong Zhu
Author-email: tzhu1997@outlook.com
Classifier: Programming Language :: Python :: 3
Classifier: License :: OSI Approved :: MIT License
Classifier: Operating System :: OS Independent
Requires-Python: >=3.7
License-File: LICENSE
Requires-Dist: numpy (>=1.19.0)
Requires-Dist: scikit-learn (>=0.21.3)
Requires-Dist: omegaconf (>=2.0.6)
Requires-Dist: loguru (>=0.5.3)
Requires-Dist: tqdm (>=4.61.1)
Requires-Dist: accelerate (>=0.9.0)
Requires-Dist: transformers (>=4.0.1)
Provides-Extra: dev
Requires-Dist: pytest ; extra == 'dev'
Requires-Dist: coverage ; extra == 'dev'
Requires-Dist: black ; extra == 'dev'
Requires-Dist: isort ; extra == 'dev'
Requires-Dist: flake8 ; extra == 'dev'
Requires-Dist: pre-commit ; extra == 'dev'
Requires-Dist: sphinx-rtd-theme ; extra == 'dev'
Requires-Dist: sphinx ; extra == 'dev'
Requires-Dist: datasets ; extra == 'dev'
